[ { "title": "hello"
 , "date": "=]"
 , "post": "hello.md"
 },
 { "title": "Blender Day 9/100 - Spinning More Space"
  , "date": "28-08-2024"
  , "post": "Day-9-Spinning-More-Space.md"
  },
 { "title": "Blender Day 8/100 - Living Scene"
  , "date": "27-08-2024"
  , "post": "Day-8-Living-Scene.md"
  },
 { "title": "Blender Day 7/100 - Planter Assets"
  , "date": "24-08-2024"
  , "post": "Day-7-Planter-Assets.md"
  },
 { "title": "Blender Day 6/100 - Assets and Textures"
  , "date": "21-08-2024"
  , "post": "Day-6-Assets-and-Textures.md"
  },
 { "title": "Blender Day 5/100 - Spaceship Assets"
  , "date": "20-08-2024"
  , "post": "Day-5-Spaceship-Assets.md"
  },
 { "title": "Blender Day 4/100 - A Scene from Scratch"
  , "date": "19-08-2024"
  , "post": "Day-4-A-Scene-from-Scratch.md"
  },
 { "title": "Blender Day 3/100 - Video Plane & Lights"
  , "date": "18-08-2024"
  , "post": "Day-3-Video-Plane-and-Lights.md"
  },
 { "title": "Blender Day 2/100 - Spinning Space"
  , "date": "17-08-2024"
  , "post": "Day-2-Spinning-Space.md"
  },
 { "title": "Blender Day 1/100 - Getting Started"
  , "date": "16-08-2024"
  , "post": "Day-1-Getting-Started.md"
  }
]
